big_bull/__init__.py
big_bull/big_bull.py
big_bull/config.py
big_bull/graph.py
big_bull/init.py
big_bull/jaeger.py
big_bull/kafka.py
big_bull/logging.py
big_bull/route.py
big_bull-0.3.25.dist-info/entry_points.txt
big_bull-0.3.25.dist-info/WHEEL
big_bull-0.3.25.dist-info/METADATA
big_bull-0.3.25.dist-info/RECORD
